compact_interval_set/__init__.py
compact_interval_set/compact_interval_set.py
compact_interval_set-0.9.dist-info/LICENSE
compact_interval_set-0.9.dist-info/METADATA
compact_interval_set-0.9.dist-info/WHEEL
compact_interval_set-0.9.dist-info/top_level.txt
compact_interval_set-0.9.dist-info/RECORD
